setup.cfg
setup.py
pyenketo/__init__.py
pyenketo.egg-info/PKG-INFO
pyenketo.egg-info/SOURCES.txt
pyenketo.egg-info/dependency_links.txt
pyenketo.egg-info/entry_points.txt
pyenketo.egg-info/not-zip-safe
pyenketo.egg-info/requires.txt
pyenketo.egg-info/top_level.txt
pyenketo/tests/__init__.py
pyenketo/tests/test_py_enketo.py