Metadata-Version: 1.0
Name: pyenketo
Version: 0.1dev
Summary: Python bindings for the Enketo API
Home-page: UNKNOWN
Author: Ona Labs
Author-email: lweya@ona.io
License: MIT
Keywords: python enketo onaio
Platform: UNKNOWN
